src/alu.v
`define WIDTH 32
`define ADD   4'b0000
`define SUB   4'b0001
`define XOR   4'b0010
`define OR    4'b0011
`define AND   4'b0100
`define SLL   4'b0101
`define SRL   4'b0110
`define SRA   4'b0111
`define SLT   4'b1000
`define SLTU  4'b1001

module alu (
    output reg [31:0] alu_out,
    input [31:0] A, B,
    input [3:0] sel,

    output zero,
    output lt_signed,
    output lt_unsigned
);

wire [4:0] shamt = B[4:0];

always @(*) begin
    case (sel)
        `ADD:  alu_out = A + B;
        `SUB:  alu_out = A - B;
        `XOR:  alu_out = A ^ B;
        `OR:   alu_out = A | B;
        `AND:  alu_out = A & B;
        `SLL:  alu_out = A << shamt;
        `SRL:  alu_out = A >> shamt;
        `SRA:  alu_out = $signed(A) >>> shamt;
        `SLT:  alu_out = ($signed(A) < $signed(B)) ? 32'b1 : 32'b0;
        `SLTU: alu_out = (A < B) ? 32'b1 : 32'b0;
        default: alu_out = 32'b0;
    endcase
end

assign zero = (alu_out == 32'b0);
assign lt_signed = ($signed(A) < $signed(B));
assign lt_unsigned = (A < B);

endmodule

testbench/alu_tb.v
`timescale 1ns/1ps

module alu_tb;

    // Testbench signals
    reg  [31:0] A, B;
    reg  [3:0]  sel;
    wire [31:0] alu_out;
    wire zero, lt_signed, lt_unsigned;

    // DUT instantiation
    alu dut (
        .A(A),
        .B(B),
        .sel(sel),
        .alu_out(alu_out),
        .zero(zero),
        .lt_signed(lt_signed),
        .lt_unsigned(lt_unsigned)
    );

    // Task for displaying results
    task show_result;
        begin
            $display("time=%0t | sel=%b | A=%0d (0x%h) | B=%0d (0x%h) | OUT=%0d (0x%h) | Z=%b | LT_S=%b | LT_U=%b",
                     $time, sel, A, A, B, B, alu_out, alu_out,
                     zero, lt_signed, lt_unsigned);
        end
    endtask

    initial begin
        $dumpfile("waveform/alu.vcd");
        $dumpvars(0, alu_tb);
        $display("===== ALU Testbench Start =====");

        // Test ADD
        A = 32'd10; B = 32'd20; sel = 4'b0000; #10; show_result();
        A = 32'h7FFF_FFFF; B = 32'd1; sel = 4'b0000; #10; show_result(); // overflow test

        // Test SUB
        A = 32'd20; B = 32'd10; sel = 4'b0001; #10; show_result();
        A = 32'h8000_0000; B = 32'd1; sel = 4'b0001; #10; show_result(); // overflow test

        // Test XOR
        A = 32'hF0F0_F0F0; B = 32'h0F0F_0F0F; sel = 4'b0010; #10; show_result();

        // Test OR
        A = 32'h1234_0000; B = 32'h0000_5678; sel = 4'b0011; #10; show_result();

        // Test AND
        A = 32'hFFFF_0000; B = 32'h00FF_00FF; sel = 4'b0100; #10; show_result();

        // Test SLL
        A = 32'h0000_0001; B = 32'd8; sel = 4'b0101; #10; show_result();

        // Test SRL
        A = 32'h8000_0000; B = 32'd4; sel = 4'b0110; #10; show_result();

        // Test SRA
        A = 32'h8000_0000; B = 32'd4; sel = 4'b0111; #10; show_result();

        // Test SLT (signed less than)
        A = -5; B = 10; sel = 4'b1000; #10; show_result();

        // Test SLTU (unsigned less than)
        A = 32'hFFFF_FFFF; B = 32'h0000_0001; sel = 4'b1001; #10; show_result();

        $display("===== ALU Testbench End =====");
        $finish;
    end

endmodule

waveform/alu.vcd
$date
	Mon Sep 15 09:41:17 2025
$end
$version
	Icarus Verilog
$end
$timescale
	1ps
$end
$scope module alu_tb $end
$var wire 1 ! zero $end
$var wire 1 " lt_unsigned $end
$var wire 1 # lt_signed $end
$var wire 32 $ alu_out [31:0] $end
$var reg 32 % A [31:0] $end
$var reg 32 & B [31:0] $end
$var reg 4 ' sel [3:0] $end
$scope module dut $end
$var wire 32 ( A [31:0] $end
$var wire 32 ) B [31:0] $end
$var wire 4 * sel [3:0] $end
$var wire 1 ! zero $end
$var wire 5 + shamt [4:0] $end
$var wire 1 " lt_unsigned $end
$var wire 1 # lt_signed $end
$var reg 32 , alu_out [31:0] $end
$upscope $end
$scope task show_result $end
$upscope $end
$upscope $end
$enddefinitions $end
$comment Show the parameter values. $end
$dumpall
$end
#0
$dumpvars
b11110 ,
b10100 +
b0 *
b10100 )
b1010 (
b0 '
b10100 &
b1010 %
b11110 $
1#
1"
0!
$end
#10000
b1 +
b10000000000000000000000000000000 $
b10000000000000000000000000000000 ,
b1 &
b1 )
0#
0"
b1111111111111111111111111111111 %
b1111111111111111111111111111111 (
#20000
b1010 +
b1010 $
b1010 ,
b1 '
b1 *
b1010 &
b1010 )
b10100 %
b10100 (
#30000
b1 +
b1111111111111111111111111111111 $
b1111111111111111111111111111111 ,
b1 &
b1 )
1#
b10000000000000000000000000000000 %
b10000000000000000000000000000000 (
#40000
b1111 +
b11111111111111111111111111111111 $
b11111111111111111111111111111111 ,
b10 '
b10 *
b1111000011110000111100001111 &
b1111000011110000111100001111 )
b11110000111100001111000011110000 %
b11110000111100001111000011110000 (
#50000
b11000 +
b10010001101000101011001111000 $
b10010001101000101011001111000 ,
b11 '
b11 *
b101011001111000 &
b101011001111000 )
0#
b10010001101000000000000000000 %
b10010001101000000000000000000 (
#60000
b11111 +
b111111110000000000000000 $
b111111110000000000000000 ,
b100 '
b100 *
b111111110000000011111111 &
b111111110000000011111111 )
1#
b11111111111111110000000000000000 %
b11111111111111110000000000000000 (
#70000
b1000 +
b100000000 $
b100000000 ,
b101 '
b101 *
b1000 &
b1000 )
1"
b1 %
b1 (
#80000
b100 +
b1000000000000000000000000000 $
b1000000000000000000000000000 ,
b110 '
b110 *
b100 &
b100 )
0"
b10000000000000000000000000000000 %
b10000000000000000000000000000000 (
#90000
b11111000000000000000000000000000 $
b11111000000000000000000000000000 ,
b111 '
b111 *
#100000
b1010 +
b1 $
b1 ,
b1000 '
b1000 *
b1010 &
b1010 )
b11111111111111111111111111111011 %
b11111111111111111111111111111011 (
#110000
b1 +
1!
b0 $
b0 ,
b1001 '
b1001 *
b1 &
b1 )
b11111111111111111111111111111111 %
b11111111111111111111111111111111 (
