src/alu.v
module alu(
    input  [31:0] A,             // rs1
    input  [31:0] B,             // rs2 or imm
    input  [3:0] sel,            // ALU op select
    output reg [31:0] alu_out,   // ALU result

    // Standard RV32I "flags"
    output zero,                 // alu_out == 0
    output lt_signed,            // A < B (signed)
    output lt_unsigned,          // A < B (unsigned)

    // Extra debug flags (not used by RV32I ISA)
    output negative,             // alu_out[31]
    output reg carry,            // carry out from add/sub
    output reg overflow          // signed overflow
);

    wire [4:0] shamt = B[4:0];   // shift amount (low 5 bits)

    // Combinational ALU
    always @(*) begin
        // Default safe values
        alu_out  = 32'd0;
        carry    = 1'b0;
        overflow = 1'b0;

        case (sel)
            4'b0000: begin // ADD
                {carry, alu_out} = {1'b0, A} + {1'b0, B};   // capture carry-out
                overflow = (A[31] == B[31]) && (alu_out[31] != A[31]);
            end
            4'b0001: begin // SUB
                {carry, alu_out} = {1'b0, A} - {1'b0, B};   // carry=borrow detect
                overflow = (A[31] != B[31]) && (alu_out[31] != A[31]);
            end
            4'b0010: alu_out = A ^ B;                       // XOR
            4'b0011: alu_out = A | B;                       // OR
            4'b0100: alu_out = A & B;                       // AND
            4'b0101: alu_out = A << shamt;                  // SLL
            4'b0110: alu_out = A >> shamt;                  // SRL
            4'b0111: alu_out = $signed(A) >>> shamt;        // SRA
            4'b1000: alu_out = ($signed(A) < $signed(B)) ? 32'd1 : 32'd0; // SLT
            4'b1001: alu_out = (A < B) ? 32'd1 : 32'd0;     // SLTU
            default: alu_out = 32'd0;
        endcase
    end

    // Derived flags
    assign zero        = (alu_out == 32'd0);
    assign negative    = alu_out[31];
    assign lt_signed   = ($signed(A) < $signed(B));
    assign lt_unsigned = (A < B);

endmodule

testbench/alu_tb2.v
`timescale 1ns/1ps

module alu_tb;

  reg  [31:0] A, B;
  reg  [3:0]  sel;
  wire [31:0] alu_out;
  wire zero, negative, carry, overflow, lt_signed, lt_unsigned;

  alu dut (
    .A(A),
    .B(B),
    .sel(sel),          
    .alu_out(alu_out),
    .zero(zero),
    .negative(negative),
    .carry(carry),
    .overflow(overflow),
    .lt_signed(lt_signed),
    .lt_unsigned(lt_unsigned)
  );


  task show_result;
    begin
      $display("time=%0t | sel=%b | A=%0d (0x%08x) | B=%0d (0x%08x) | OUT=%0d (0x%08x) | Z=%b N=%b C=%b V=%b | LT_S=%b LT_U=%b",
        $time, sel, A, A, B, B, alu_out, alu_out, zero, negative, carry, overflow, lt_signed, lt_unsigned);
    end
  endtask

  initial begin
    $dumpfile("waveform/alu2.vcd");
    $dumpvars(0, alu_tb);

    $display("===== ALU Testbench Start =====");

    // Existing tests
    #10 sel = 4'b0000; A = 10; B = 20; #10 show_result();   // ADD
    #10 sel = 4'b0000; A = 32'h7fffffff; B = 1; #10 show_result();
    #10 sel = 4'b0001; A = 20; B = 10; #10 show_result();   // SUB
    #10 sel = 4'b0001; A = 32'h80000000; B = 1; #10 show_result();
    #10 sel = 4'b0010; A = 32'hf0f0f0f0; B = 32'h0f0f0f0f; #10 show_result(); // OR
    #10 sel = 4'b0011; A = 32'h12340000; B = 32'h5678; #10 show_result(); // ADD
    #10 sel = 4'b0100; A = 32'hffff0000; B = 32'h00ff00ff; #10 show_result(); // AND
    #10 sel = 4'b0101; A = 32'h1; B = 8; #10 show_result(); // SLL
    #10 sel = 4'b0110; A = 32'h80000000; B = 4; #10 show_result(); // SRL
    #10 sel = 4'b0111; A = 32'h80000000; B = 4; #10 show_result(); // SRA
    #10 sel = 4'b1000; A = -5; B = 10; #10 show_result(); // SLT signed
    #10 sel = 4'b1001; A = 32'hffffffff; B = 1; #10 show_result(); // SLTU

    // ====== NEW edge case tests ======
    #10 sel = 4'b0000; A = 32'hffffffff; B = 1; #10 show_result();  
      // ADD: unsigned carry should be 1, result=0
    #10 sel = 4'b0000; A = 32'h80000000; B = 32'h80000000; #10 show_result();  
      // ADD: signed overflow, carry=1, result=0
    #10 sel = 4'b0001; A = 0; B = 1; #10 show_result();    
      // SUB: borrow occurs, carry flag check
    #10 sel = 4'b0001; A = 32'h7fffffff; B = 32'hffffffff; #10 show_result();  
      // SUB: positive - (-1) = overflow check

    $display("===== ALU Testbench End =====");
    $finish;
  end
endmodule

waveform/alu2.vcd
$date
	Fri Aug 22 11:32:40 2025
$end
$version
	Icarus Verilog
$end
$timescale
	1ps
$end
$scope module alu_tb $end
$var wire 1 ! zero $end
$var wire 1 " overflow $end
$var wire 1 # negative $end
$var wire 1 $ lt_unsigned $end
$var wire 1 % lt_signed $end
$var wire 1 & carry $end
$var wire 32 ' alu_out [31:0] $end
$var reg 32 ( A [31:0] $end
$var reg 32 ) B [31:0] $end
$var reg 4 * sel [3:0] $end
$scope module dut $end
$var wire 32 + A [31:0] $end
$var wire 32 , B [31:0] $end
$var wire 4 - sel [3:0] $end
$var wire 1 ! zero $end
$var wire 5 . shamt [4:0] $end
$var wire 1 # negative $end
$var wire 1 $ lt_unsigned $end
$var wire 1 % lt_signed $end
$var reg 32 / alu_out [31:0] $end
$var reg 1 & carry $end
$var reg 1 " overflow $end
$upscope $end
$scope task show_result $end
$upscope $end
$upscope $end
$enddefinitions $end
$comment Show the parameter values. $end
$dumpall
$end
#0
$dumpvars
bx /
bx .
bx -
bx ,
bx +
bx *
bx )
bx (
bx '
x&
x%
x$
x#
x"
x!
$end
#10000
0#
b10100 .
0"
0&
0!
b11110 '
b11110 /
1%
1$
b10100 )
b10100 ,
b1010 (
b1010 +
b0 *
b0 -
#30000
1#
b1 .
1"
0!
b10000000000000000000000000000000 '
b10000000000000000000000000000000 /
b1 )
b1 ,
0%
0$
b1111111111111111111111111111111 (
b1111111111111111111111111111111 +
#50000
0#
b1010 .
0"
0!
b1010 '
b1010 /
b1010 )
b1010 ,
b10100 (
b10100 +
b1 *
b1 -
#70000
b1 .
1"
0!
b1111111111111111111111111111111 '
b1111111111111111111111111111111 /
b1 )
b1 ,
1%
b10000000000000000000000000000000 (
b10000000000000000000000000000000 +
#90000
1#
b1111 .
0"
0!
b11111111111111111111111111111111 '
b11111111111111111111111111111111 /
b1111000011110000111100001111 )
b1111000011110000111100001111 ,
b11110000111100001111000011110000 (
b11110000111100001111000011110000 +
b10 *
b10 -
#110000
0#
b11000 .
0!
b10010001101000101011001111000 '
b10010001101000101011001111000 /
b101011001111000 )
b101011001111000 ,
0%
b10010001101000000000000000000 (
b10010001101000000000000000000 +
b11 *
b11 -
#130000
b11111 .
0!
b111111110000000000000000 '
b111111110000000000000000 /
b111111110000000011111111 )
b111111110000000011111111 ,
1%
b11111111111111110000000000000000 (
b11111111111111110000000000000000 +
b100 *
b100 -
#150000
0#
b1000 .
0!
b100000000 '
b100000000 /
b1000 )
b1000 ,
1$
b1 (
b1 +
b101 *
b101 -
#170000
b100 .
0!
b1000000000000000000000000000 '
b1000000000000000000000000000 /
b100 )
b100 ,
0$
b10000000000000000000000000000000 (
b10000000000000000000000000000000 +
b110 *
b110 -
#190000
1#
0!
b11111000000000000000000000000000 '
b11111000000000000000000000000000 /
b111 *
b111 -
#210000
0#
b1010 .
0!
b1 '
b1 /
b1010 )
b1010 ,
b11111111111111111111111111111011 (
b11111111111111111111111111111011 +
b1000 *
b1000 -
#230000
b1 .
1!
b0 '
b0 /
b1 )
b1 ,
b11111111111111111111111111111111 (
b11111111111111111111111111111111 +
b1001 *
b1001 -
#250000
1&
b0 *
b0 -
#270000
b0 .
1"
1&
0%
b10000000000000000000000000000000 )
b10000000000000000000000000000000 ,
b10000000000000000000000000000000 (
b10000000000000000000000000000000 +
#290000
1#
b1 .
0!
b11111111111111111111111111111111 '
b11111111111111111111111111111111 /
0"
1&
1%
b1 )
b1 ,
1$
b0 (
b0 +
b1 *
b1 -
#310000
b11111 .
1"
1&
0!
b10000000000000000000000000000000 '
b10000000000000000000000000000000 /
b11111111111111111111111111111111 )
b11111111111111111111111111111111 ,
0%
1$
b1111111111111111111111111111111 (
b1111111111111111111111111111111 +
