src/pc.v
module pc(
    output reg [31:0] pc_out,
    input [31:0] pc_in,
    input clk, rst, pc_jmp
);
always @(posedge clk or posedge rst)begin
    if (rst)begin
        pc_out <= 32'h00000000;
    end else if (pc_jmp) begin
        pc_out <= pc_in; // pc_out = pc_in if pc_jump HIGH and posedge clk
    end else begin
        pc_out <= pc_out + 32'h00000004; // increment by 4 every posedge
    end
end
endmodule

testbench/pc_tb.v
`timescale 1ns/1ps

module pc_tb;

  reg clk;
  reg rst;
  reg pc_jmp;
  reg [31:0] pc_in;
  wire [31:0] pc_out;

  // Instantiate the pc module
  pc uut (
    .pc_out(pc_out),
    .pc_in(pc_in),
    .clk(clk),
    .rst(rst),
    .pc_jmp(pc_jmp)
  );

  // Clock generation: 10ns period
  initial begin
    clk = 0;
    forever #5 clk = ~clk;
  end

  initial begin
    // Dump waveform and monitor
    $dumpfile("waveform/pc.vcd");
    $dumpvars(0, pc_tb);

    // Initialize inputs
    rst = 1;
    pc_jmp = 0;
    pc_in = 32'h00000000;

    // Hold reset for 20ns
    #20;
    rst = 0;

    // Wait for a few clock cycles to see increment
    #40;

    // Test jump: load pc_in = 0x1000 and assert pc_jmp
    pc_in = 32'h00001000;
    pc_jmp = 1;
    #10;
    pc_jmp = 0;

    // Wait and see increment from 0x1000
    #40;

    // Test another jump
    pc_in = 32'hFFFFFFFC;
    pc_jmp = 1;
    #10;
    pc_jmp = 0;

    // Wait some cycles
    #40;

    // Finish simulation
    $finish;
  end

endmodule

waveform/pc.vcd
$date
	Fri Aug 29 23:14:22 2025
$end
$version
	Icarus Verilog
$end
$timescale
	1ps
$end
$scope module pc_tb $end
$var wire 32 ! pc_out [31:0] $end
$var reg 1 " clk $end
$var reg 32 # pc_in [31:0] $end
$var reg 1 $ pc_jmp $end
$var reg 1 % rst $end
$scope module uut $end
$var wire 1 " clk $end
$var wire 32 & pc_in [31:0] $end
$var wire 1 $ pc_jmp $end
$var wire 1 % rst $end
$var reg 32 ' pc_out [31:0] $end
$upscope $end
$upscope $end
$enddefinitions $end
$comment Show the parameter values. $end
$dumpall
$end
#0
$dumpvars
b0 '
b0 &
1%
0$
b0 #
0"
b0 !
$end
#5000
1"
#10000
0"
#15000
1"
#20000
0"
0%
#25000
b100 !
b100 '
1"
#30000
0"
#35000
b1000 !
b1000 '
1"
#40000
0"
#45000
b1100 !
b1100 '
1"
#50000
0"
#55000
b10000 !
b10000 '
1"
#60000
0"
1$
b1000000000000 #
b1000000000000 &
#65000
b1000000000000 !
b1000000000000 '
1"
#70000
0"
0$
#75000
b1000000000100 !
b1000000000100 '
1"
#80000
0"
#85000
b1000000001000 !
b1000000001000 '
1"
#90000
0"
#95000
b1000000001100 !
b1000000001100 '
1"
#100000
0"
#105000
b1000000010000 !
b1000000010000 '
1"
#110000
0"
1$
b11111111111111111111111111111100 #
b11111111111111111111111111111100 &
#115000
b11111111111111111111111111111100 !
b11111111111111111111111111111100 '
1"
#120000
0"
0$
#125000
b0 !
b0 '
1"
#130000
0"
#135000
b100 !
b100 '
1"
#140000
0"
#145000
b1000 !
b1000 '
1"
#150000
0"
#155000
b1100 !
b1100 '
1"
