src/register_file.v
module register_file(
    output [31:0] rs1_data, rs2_data,
    input [31:0] rd_data,
    input [4:0] rs1, rs2, rd,
    input clk, rst, reg_write
);

// 32 general-purpose 32-bit registers
reg [31:0] register [31:0];

// Read logic (combinational)
assign rs1_data = (rs1 == 5'd0) ? 32'b0 : register[rs1];
assign rs2_data = (rs2 == 5'd0) ? 32'b0 : register[rs2];

// Write and reset logic (synchronous)
integer i;
always @(posedge clk) begin
    if (rst) begin
        for (i = 0; i < 32; i = i + 1)
        register[i] <= 32'b0;  //hardwires the 'x0' register to zero
        end else if (reg_write && (rd != 5'd0)) begin
            register[rd] <= rd_data;
        end
end

endmodule

testbench/register_tb.v
`timescale 1ns/1ps

module register_tb;

    // Inputs
    reg clk;
    reg rst;
    reg reg_write;
    reg [4:0] rs1, rs2, rd;
    reg [31:0] rd_data;

    // Outputs
    wire [31:0] rs1_data, rs2_data;

    // Instantiate the register file
    register_file uut (
        .rs1_data(rs1_data),
        .rs2_data(rs2_data),
        .rd_data(rd_data),
        .rs1(rs1),
        .rs2(rs2),
        .rd(rd),
        .clk(clk),
        .rst(rst),
        .reg_write(reg_write)
    );

    // Clock generator: 10ns period
    always #5 clk = ~clk;

    initial begin
        $dumpfile("waveform/register_file.vcd");
        $dumpvars(0,register_tb);
        // Initial values
        clk = 0;
        rst = 0;
        reg_write = 0;
        rs1 = 0;
        rs2 = 0;
        rd = 0;
        rd_data = 0;

        $display("Starting Register File Testbench");
        $monitor("Time=%0t | rs1=%d rs2=%d rd=%d | rs1_data=%h rs2_data=%h | reg_write=%b rd_data=%h",
                 $time, rs1, rs2, rd, rs1_data, rs2_data, reg_write, rd_data);

        // Apply reset
        #2 rst = 1;
        #10 rst = 0;

        // Try to write to x0 (should not change)
        reg_write = 1;
        rd = 5'd0;
        rd_data = 32'hDEADBEEF;
        #10;

        rs1 = 5'd0; rs2 = 5'd0;
        #2;
        $display("x0 readback (should be 0): rs1_data=%h", rs1_data);

        // Write to register 5
        rd = 5'd5;
        rd_data = 32'hCAFEBABE;
        #10;

        // Read from register 5
        reg_write = 0;
        rs1 = 5'd5;
        rs2 = 5'd0;
        #2;
        $display("Readback from reg[5] (should be CAFEBABE): rs1_data=%h", rs1_data);

        // Write to register 10
        reg_write = 1;
        rd = 5'd10;
        rd_data = 32'h12345678;
        #10;

        // Read from register 10
        reg_write = 0;
        rs1 = 5'd10;
        rs2 = 5'd5;
        #2;
        $display("rs1=reg[10]=%h, rs2=reg[5]=%h", rs1_data, rs2_data);

        // Assert reset again and check cleared registers
        rst = 1;
        #10 rst = 0;
        rs1 = 5'd5;
        rs2 = 5'd10;
        #2;
        $display("After reset again: reg[5]=%h, reg[10]=%h", rs1_data, rs2_data);

        $finish;
    end

endmodule

waveform/register_file.vcd
$date
	Fri Aug 22 10:47:19 2025
$end
$version
	Icarus Verilog
$end
$timescale
	1ps
$end
$scope module register_tb $end
$var wire 32 ! rs2_data [31:0] $end
$var wire 32 " rs1_data [31:0] $end
$var reg 1 # clk $end
$var reg 5 $ rd [4:0] $end
$var reg 32 % rd_data [31:0] $end
$var reg 1 & reg_write $end
$var reg 5 ' rs1 [4:0] $end
$var reg 5 ( rs2 [4:0] $end
$var reg 1 ) rst $end
$scope module uut $end
$var wire 1 # clk $end
$var wire 5 * rd [4:0] $end
$var wire 32 + rd_data [31:0] $end
$var wire 1 & reg_write $end
$var wire 5 , rs1 [4:0] $end
$var wire 5 - rs2 [4:0] $end
$var wire 1 ) rst $end
$var wire 32 . rs2_data [31:0] $end
$var wire 32 / rs1_data [31:0] $end
$var integer 32 0 i [31:0] $end
$upscope $end
$upscope $end
$enddefinitions $end
$comment Show the parameter values. $end
$dumpall
$end
#0
$dumpvars
bx 0
b0 /
b0 .
b0 -
b0 ,
b0 +
b0 *
0)
b0 (
b0 '
0&
b0 %
b0 $
0#
b0 "
b0 !
$end
#2000
1)
#5000
b100000 0
1#
#10000
0#
#12000
b11011110101011011011111011101111 %
b11011110101011011011111011101111 +
1&
0)
#15000
1#
#20000
0#
#24000
b11001010111111101011101010111110 %
b11001010111111101011101010111110 +
b101 $
b101 *
#25000
1#
#30000
0#
#34000
b11001010111111101011101010111110 "
b11001010111111101011101010111110 /
b101 '
b101 ,
0&
#35000
1#
#36000
b10010001101000101011001111000 %
b10010001101000101011001111000 +
b1010 $
b1010 *
1&
#40000
0#
#45000
1#
#46000
b11001010111111101011101010111110 !
b11001010111111101011101010111110 .
b10010001101000101011001111000 "
b10010001101000101011001111000 /
b101 (
b101 -
b1010 '
b1010 ,
0&
#48000
1)
#50000
0#
#55000
b0 "
b0 /
b0 !
b0 .
b100000 0
1#
#58000
b1010 (
b1010 -
b101 '
b101 ,
0)
